{
    "name": "race_5",
    "start time": "2022-09-23 11:12:06.823253",
    "attack_config": {
        "train_config": {
            "data_config": {
                "name": "new_census",
                "prop": "race",
                "value": 0.5,
                "split": "adv",
                "drop_senstive_cols": false,
                "scale": 1.0,
                "augment": false,
                "classify": null,
                "cwise_samples": null,
                "squeeze": true,
                "processed_variant": true,
                "prune": 0
            },
            "epochs": 0,
            "learning_rate": 0.0,
            "batch_size": 0,
            "misc_config": null,
            "lr_scheduler": null,
            "verbose": false,
            "num_models": 1,
            "offset": 0,
            "weight_decay": 0,
            "get_best": true,
            "cpu": false,
            "expect_extra": true,
            "save_every_epoch": false,
            "extra_info": null,
            "regression": false,
            "multi_class": false,
            "label_noise": 0,
            "model_arch": null,
            "parallel": false
        },
        "values": [
            0.0,
            0.1,
            0.2,
            0.3,
            0.4,
            0.6,
            0.7,
            0.8,
            0.9,
            1.0
        ],
        "black_box": {
            "attack_type": [
                "KL"
            ],
            "ratios": [
                1.0
            ],
            "batch_size": 30000,
            "num_adv_models": 5,
            "granularity": 0.05,
            "preload": true,
            "multi": null,
            "multi2": null,
            "multi_class": false,
            "save": false,
            "tune_final_threshold": false,
            "Start_epoch": 1,
            "End_epoch": 20,
            "relative_threshold": false,
            "loss_variant": false,
            "random_order": false,
            "kl_frac": 0.8,
            "kl_voting": false,
            "generative_attack": null,
            "order_name": null,
            "geo_mean": false,
            "regression_config": null
        },
        "white_box": null,
        "tries": 5,
        "num_victim_models": 250,
        "on_cpu": false,
        "adv_misc_config": null,
        "num_total_adv_models": 1000,
        "victim_local_attack": false,
        "victim_model_arch": null,
        "adv_model_arch": null,
        "adv_processed_variant": false,
        "adv_target_epoch": null,
        "victim_target_epoch": null
    },
    "result": {
        "KL": {
            "0.0": {
                "adv_acc": [
                    null,
                    null,
                    null,
                    null,
                    null
                ],
                "victim_acc": [
                    99.8,
                    100.0,
                    100.0,
                    100.0,
                    100.0
                ]
            },
            "0.1": {
                "adv_acc": [
                    null,
                    null,
                    null,
                    null,
                    null
                ],
                "victim_acc": [
                    95.6,
                    97.2,
                    98.2,
                    98.6,
                    99.0
                ]
            },
            "0.2": {
                "adv_acc": [
                    null,
                    null,
                    null,
                    null,
                    null
                ],
                "victim_acc": [
                    88.2,
                    85.8,
                    88.6,
                    76.6,
                    82.6
                ]
            },
            "0.3": {
                "adv_acc": [
                    null,
                    null,
                    null,
                    null,
                    null
                ],
                "victim_acc": [
                    69.8,
                    68.0,
                    56.2,
                    71.2,
                    68.60000000000001
                ]
            },
            "0.4": {
                "adv_acc": [
                    null,
                    null,
                    null,
                    null,
                    null
                ],
                "victim_acc": [
                    53.800000000000004,
                    60.4,
                    54.2,
                    51.2,
                    52.2
                ]
            },
            "0.6": {
                "adv_acc": [
                    null,
                    null,
                    null,
                    null,
                    null
                ],
                "victim_acc": [
                    49.8,
                    50.4,
                    53.2,
                    56.2,
                    51.6
                ]
            },
            "0.7": {
                "adv_acc": [
                    null,
                    null,
                    null,
                    null,
                    null
                ],
                "victim_acc": [
                    62.0,
                    62.2,
                    56.599999999999994,
                    61.4,
                    57.599999999999994
                ]
            },
            "0.8": {
                "adv_acc": [
                    null,
                    null,
                    null,
                    null,
                    null
                ],
                "victim_acc": [
                    69.8,
                    78.4,
                    73.2,
                    64.4,
                    61.0
                ]
            },
            "0.9": {
                "adv_acc": [
                    null,
                    null,
                    null,
                    null,
                    null
                ],
                "victim_acc": [
                    78.4,
                    84.8,
                    84.6,
                    80.0,
                    85.2
                ]
            },
            "1.0": {
                "adv_acc": [
                    null,
                    null,
                    null,
                    null,
                    null
                ],
                "victim_acc": [
                    98.2,
                    98.4,
                    97.2,
                    98.4,
                    98.4
                ]
            }
        }
    },
    "save time": "2022-09-23 13:25:27.420568"
}