{
    "name": "race_10",
    "start time": "2022-09-23 14:20:50.628673",
    "attack_config": {
        "train_config": {
            "data_config": {
                "name": "new_census",
                "prop": "race",
                "value": 0.5,
                "split": "adv",
                "drop_senstive_cols": false,
                "scale": 1.0,
                "augment": false,
                "classify": null,
                "cwise_samples": null,
                "squeeze": true,
                "processed_variant": true,
                "prune": 0
            },
            "epochs": 0,
            "learning_rate": 0.0,
            "batch_size": 0,
            "misc_config": null,
            "lr_scheduler": null,
            "verbose": false,
            "num_models": 1,
            "offset": 0,
            "weight_decay": 0,
            "get_best": true,
            "cpu": false,
            "expect_extra": true,
            "save_every_epoch": false,
            "extra_info": null,
            "regression": false,
            "multi_class": false,
            "label_noise": 0,
            "model_arch": null,
            "parallel": false
        },
        "values": [
            0.0,
            0.1,
            0.2,
            0.3,
            0.4,
            0.6,
            0.7,
            0.8,
            0.9,
            1.0
        ],
        "black_box": {
            "attack_type": [
                "KL"
            ],
            "ratios": [
                1.0
            ],
            "batch_size": 30000,
            "num_adv_models": 10,
            "granularity": 0.05,
            "preload": true,
            "multi": null,
            "multi2": null,
            "multi_class": false,
            "save": false,
            "tune_final_threshold": false,
            "Start_epoch": 1,
            "End_epoch": 20,
            "relative_threshold": false,
            "loss_variant": false,
            "random_order": false,
            "kl_frac": 0.8,
            "kl_voting": false,
            "generative_attack": null,
            "order_name": null,
            "geo_mean": false,
            "regression_config": null
        },
        "white_box": null,
        "tries": 5,
        "num_victim_models": 250,
        "on_cpu": false,
        "adv_misc_config": null,
        "num_total_adv_models": 1000,
        "victim_local_attack": false,
        "victim_model_arch": null,
        "adv_model_arch": null,
        "adv_processed_variant": false,
        "adv_target_epoch": null,
        "victim_target_epoch": null
    },
    "result": {
        "KL": {
            "0.0": {
                "adv_acc": [
                    null,
                    null,
                    null,
                    null,
                    null
                ],
                "victim_acc": [
                    100.0,
                    100.0,
                    100.0,
                    99.8,
                    100.0
                ]
            },
            "0.1": {
                "adv_acc": [
                    null,
                    null,
                    null,
                    null,
                    null
                ],
                "victim_acc": [
                    99.6,
                    98.6,
                    99.2,
                    98.6,
                    99.0
                ]
            },
            "0.2": {
                "adv_acc": [
                    null,
                    null,
                    null,
                    null,
                    null
                ],
                "victim_acc": [
                    88.8,
                    85.39999999999999,
                    85.8,
                    92.80000000000001,
                    89.8
                ]
            },
            "0.3": {
                "adv_acc": [
                    null,
                    null,
                    null,
                    null,
                    null
                ],
                "victim_acc": [
                    69.6,
                    65.60000000000001,
                    71.6,
                    67.4,
                    75.2
                ]
            },
            "0.4": {
                "adv_acc": [
                    null,
                    null,
                    null,
                    null,
                    null
                ],
                "victim_acc": [
                    59.199999999999996,
                    56.599999999999994,
                    54.2,
                    55.400000000000006,
                    54.800000000000004
                ]
            },
            "0.6": {
                "adv_acc": [
                    null,
                    null,
                    null,
                    null,
                    null
                ],
                "victim_acc": [
                    50.0,
                    55.2,
                    54.0,
                    55.400000000000006,
                    52.0
                ]
            },
            "0.7": {
                "adv_acc": [
                    null,
                    null,
                    null,
                    null,
                    null
                ],
                "victim_acc": [
                    59.599999999999994,
                    61.0,
                    63.0,
                    66.4,
                    66.0
                ]
            },
            "0.8": {
                "adv_acc": [
                    null,
                    null,
                    null,
                    null,
                    null
                ],
                "victim_acc": [
                    79.2,
                    75.2,
                    75.2,
                    78.8,
                    75.4
                ]
            },
            "0.9": {
                "adv_acc": [
                    null,
                    null,
                    null,
                    null,
                    null
                ],
                "victim_acc": [
                    90.60000000000001,
                    90.2,
                    89.0,
                    86.0,
                    89.2
                ]
            },
            "1.0": {
                "adv_acc": [
                    null,
                    null,
                    null,
                    null,
                    null
                ],
                "victim_acc": [
                    99.0,
                    97.6,
                    97.8,
                    98.8,
                    98.8
                ]
            }
        }
    },
    "save time": "2022-09-23 16:34:52.105033"
}