{
    "name": "victim_age_bonemodel_0.8_3000",
    "start time": "2022-08-28 16:17:43.097604",
    "train_config": {
        "data_config": {
            "name": "boneage",
            "prop": "age",
            "value": 0.8,
            "split": "victim",
            "drop_senstive_cols": false,
            "scale": 1.0,
            "augment": false,
            "classify": "gender",
            "cwise_samples": null,
            "squeeze": true,
            "processed_variant": true,
            "prune": 0
        },
        "epochs": 20,
        "learning_rate": 0.002,
        "batch_size": 8192,
        "misc_config": null,
        "lr_scheduler": null,
        "verbose": false,
        "num_models": 6,
        "offset": 3000,
        "weight_decay": 0.02,
        "get_best": true,
        "cpu": false,
        "expect_extra": true,
        "save_every_epoch": false,
        "extra_info": null,
        "regression": false,
        "multi_class": false,
        "label_noise": 0,
        "model_arch": "bonemodel",
        "parallel": false
    },
    "log": {
        "0.8": {
            "loss": [
                0.6535400152206421
            ],
            "acc": [
                0.6565389696169088
            ]
        }
    },
    "save time": "2022-08-28 16:17:56.923011"
}