{
    "name": "affinity_sex_ultimate_120",
    "start time": "2022-04-15 15:24:36.945540",
    "attack_config": {
        "train_config": {
            "data_config": {
                "name": "new_census",
                "prop": "sex",
                "value": 0.5,
                "split": "adv",
                "drop_senstive_cols": false,
                "scale": 1.0,
                "augment": false,
                "classify": null,
                "cwise_samples": null,
                "squeeze": true
            },
            "epochs": 0,
            "learning_rate": 0.0,
            "batch_size": 0,
            "misc_config": null,
            "verbose": false,
            "num_models": 1,
            "offset": 0,
            "weight_decay": 0,
            "get_best": true,
            "cpu": false,
            "expect_extra": true,
            "save_every_epoch": false,
            "extra_info": null
        },
        "values": [
            0.0,
            0.1,
            0.2,
            0.3,
            0.4,
            0.6,
            0.7,
            0.8,
            0.9,
            1.0
        ],
        "black_box": null,
        "white_box": {
            "attack": "affinity",
            "epochs": 120,
            "batch_size": 1000,
            "learning_rate": 0.001,
            "weight_decay": 0.01,
            "train_sample": 800,
            "val_sample": 0,
            "save": false,
            "load": null,
            "regression_config": null,
            "eval_every": 10,
            "binary": true,
            "gpu": true,
            "shuffle": true,
            "custom_layers_fc": null,
            "start_n_fc": 0,
            "first_n_fc": null,
            "custom_layers_conv": null,
            "start_n_conv": 0,
            "first_n_conv": null,
            "permutation_config": null,
            "affinity_config": {
                "num_final": 16,
                "only_latent": false,
                "frac_retain_pairs": 0.2,
                "num_samples_use": 40,
                "layer_agnostic": false,
                "inner_dims": [
                    128,
                    32
                ],
                "shared_layerwise_params": true
            }
        },
        "tries": 5,
        "num_victim_models": 1000,
        "on_cpu": false,
        "adv_diff_misc_config": true,
        "adv_misc_config": null,
        "num_total_adv_models": 1000
    },
    "result": {
        "affinity": {
            "0.0": {
                "adv_acc": [
                    null,
                    null,
                    null,
                    null,
                    null
                ],
                "victim_acc": [
                    100.0,
                    99.95,
                    100.0,
                    100.0,
                    100.0
                ]
            },
            "0.1": {
                "adv_acc": [
                    null,
                    null,
                    null,
                    null,
                    null
                ],
                "victim_acc": [
                    93.9,
                    94.15,
                    93.39999999999999,
                    95.05,
                    93.15
                ]
            },
            "0.2": {
                "adv_acc": [
                    null,
                    null,
                    null,
                    null,
                    null
                ],
                "victim_acc": [
                    87.4,
                    89.25,
                    82.3,
                    84.15,
                    87.6
                ]
            },
            "0.3": {
                "adv_acc": [
                    null,
                    null,
                    null,
                    null,
                    null
                ],
                "victim_acc": [
                    74.75,
                    77.85,
                    78.3,
                    75.8,
                    78.3
                ]
            },
            "0.4": {
                "adv_acc": [
                    null,
                    null,
                    null,
                    null,
                    null
                ],
                "victim_acc": [
                    57.199999999999996,
                    60.25,
                    59.199999999999996,
                    50.0,
                    58.45
                ]
            },
            "0.6": {
                "adv_acc": [
                    null,
                    null,
                    null,
                    null,
                    null
                ],
                "victim_acc": [
                    50.0,
                    50.0,
                    64.7,
                    59.050000000000004,
                    63.650000000000006
                ]
            },
            "0.7": {
                "adv_acc": [
                    null,
                    null,
                    null,
                    null,
                    null
                ],
                "victim_acc": [
                    81.35,
                    84.05,
                    73.05,
                    82.6,
                    79.69999999999999
                ]
            },
            "0.8": {
                "adv_acc": [
                    null,
                    null,
                    null,
                    null,
                    null
                ],
                "victim_acc": [
                    90.7,
                    87.75,
                    75.55000000000001,
                    89.95,
                    93.19999999999999
                ]
            },
            "0.9": {
                "adv_acc": [
                    null,
                    null,
                    null,
                    null,
                    null
                ],
                "victim_acc": [
                    97.1,
                    90.95,
                    96.0,
                    95.1,
                    93.45
                ]
            },
            "1.0": {
                "adv_acc": [
                    null,
                    null,
                    null,
                    null,
                    null
                ],
                "victim_acc": [
                    99.75,
                    99.95,
                    99.05,
                    99.8,
                    99.5
                ]
            }
        }
    },
    "save time": "2022-04-16 00:56:30.530553"
}